[
    {
        "audio": "audio/GKwRIUEI2QiJAZWiEQJaslfN-aacv2-48K_10_input.wav",
        "task": {
            "name": "识别声音发生的场景",
            "label": "indoor",
            "answer": "是在室内的。"
        }
    },
    {
        "audio": "audio/logMQUdrdkmgCfKTjQ3BSirNomIE_1_input.wav",
        "task": {
            "name": "识别声音发生的场景",
            "label": "kitchen",
            "answer": "是在厨房。"
        }
    },
    {
        "audio": "audio/luFfVf3hsNp9E33mU4G34BCRds-B_15_input.wav",
        "task": {
            "name": "识别声音发生的场景",
            "label": "outdoor",
            "answer": "这是在户外录的。"
        }
    },
    {
        "audio": "audio/lrJjkV-kUaiayGq_XZEtdi7QyK2a_17_input.wav",
        "task": {
            "name": "识别声音发生的场景",
            "label": "outdoor",
            "answer": "我觉得这是在户外录制的。"
        }
    },
    {
        "audio": "audio/lmKlyXvOvVUppXQeBpTbxNBzjuzd_5_input.wav",
        "task": {
            "name": "识别声音发生的场景",
            "label": "outdoor",
            "answer": "是在户外。"
        }
    },
    {
        "audio": "audio/GKwRIJIFo7ckABAAAAEIlrML_6_input.wav",
        "task": {
            "name": "识别声音发生的场景",
            "label": "indoor",
            "answer": "这是在室内的。"
        }
    },
    {
        "audio": "audio/WPDL_uDpdCdhCVwQLUnkrAwzrNRBNbQThCbrDpmexUpQCvwnwnJDHRarKEvKbJM-4a_3_input.wav",
        "task": {
            "name": "识别声音发生的场景",
            "label": "restaurant",
            "answer": "这是在餐厅录的。"
        }
    },
    {
        "audio": "audio/lnvRtl2mY6pQ92noHfzWSuKqmNt7_22_input.wav",
        "task": {
            "name": "识别声音发生的场景",
            "label": "outdoor",
            "answer": "这个声音是在室外发生的。"
        }
    },
    {
        "audio": "audio/CKwRIW4EfgiLAdPS1QCuktI0_18_input.wav",
        "task": {
            "name": "识别声音发生的场景",
            "label": "restaurant",
            "answer": "这是在餐厅里录的。"
        }
    },
    {
        "audio": "audio/lmG_zTGHwIsKeHkHl2MCAaaqq7uq_13_input.wav",
        "task": {
            "name": "识别声音发生的场景",
            "label": "outdoor",
            "answer": "这个声音是在户外发生的。"
        }
    },
    {
        "audio": "audio/WPDL_bNkcAGkaKyzHHtJphjnvAmcBxjxdARtVWtZauqgjrDeWdjqNXbRpavGhwX-54_14_input.wav",
        "task": {
            "name": "识别声音发生的场景",
            "label": "kitchen",
            "answer": "是在厨房录制的。"
        }
    },
    {
        "audio": "audio/GKwRIJEGuQR9AbF8xwGKLB1E_15_input.wav",
        "task": {
            "name": "识别声音发生的场景",
            "label": "subway",
            "answer": "这段声音最有可能发生在地铁站。"
        }
    },
    {
        "audio": "audio/lr0__gwNCdFSaLvzDoMjiqgz1HGo_30_input.wav",
        "task": {
            "name": "识别声音发生的场景",
            "label": "subway",
            "answer": "这是在地铁站。"
        }
    },
    {
        "audio": "audio/lkg3WxUcGVCcPCRB7gELEo2PqIyi_14_input.wav",
        "task": {
            "name": "识别声音发生的场景",
            "label": "outdoor",
            "answer": "声音是在户外发生的。"
        }
    },
    {
        "audio": "audio/lk1pGRpYZ-vM84DWBW6yW8VGR2jt_6_input.wav",
        "task": {
            "name": "识别声音发生的场景",
            "label": "restaurant",
            "answer": "这段声音最有可能是在餐厅里录制的。"
        }
    },
    {
        "audio": "audio/lm60CW4TOJNdtHlwefTEow-5goog_25_input.wav",
        "task": {
            "name": "识别声音发生的场景",
            "label": "outdoor",
            "answer": "这是在户外录的。"
        }
    },
    {
        "audio": "audio/lmq06Z218f8y2nLalFvsoEDhhNm__0_input.wav",
        "task": {
            "name": "识别声音发生的场景",
            "label": "indoor",
            "answer": "是在室内的。"
        }
    },
    {
        "audio": "audio/GKwRIJEJ30bWAxI5XALADZ5k-aacv2-48K_4_input.wav",
        "task": {
            "name": "识别声音发生的场景",
            "label": "indoor",
            "answer": "这是在室内的地方录的。"
        }
    },
    {
        "audio": "audio/WPDL_cJduUGAtbjPFweYHRUvSkqNkDuDnBEFKmvgJgKgATMNHYruQZSbHtBHVQc-53_2_input.wav",
        "task": {
            "name": "识别声音发生的场景",
            "label": "indoor",
            "answer": "是在室内录的。"
        }
    },
    {
        "audio": "audio/liBFQNEYUYEgYzX5d6y28rlKFvsq_9_input.wav",
        "task": {
            "name": "识别声音发生的场景",
            "label": "park",
            "answer": "这是在公园录的音。"
        }
    },
    {
        "audio": "audio/lrY4UcRLedPN5eVco6n6r1Daetzo_14_input.wav",
        "task": {
            "name": "识别声音发生的场景",
            "label": "restaurant",
            "answer": "这是在餐厅录的。"
        }
    },
    {
        "audio": "audio/2023-04-29-XQPod-Sarah-Final_21_input.wav",
        "task": {
            "name": "识别声音发生的场景",
            "label": "park",
            "answer": "这是在公园里。"
        }
    },
    {
        "audio": "audio/lkv8PNtq-3FaZh2fxOLhWTCw8iWm_6_input.wav",
        "task": {
            "name": "识别声音发生的场景",
            "label": "indoor",
            "answer": "这是在室内的。"
        }
    },
    {
        "audio": "audio/llYByV_xMfmfwtZ31QgCO80Q2Soi_22_input.wav",
        "task": {
            "name": "识别声音发生的场景",
            "label": "restaurant",
            "answer": "这是在餐厅里的声音。"
        }
    },
    {
        "audio": "audio/GKwRIaIJEpJCAg-4OgJ07w-B-aacv2-48K_3_input.wav",
        "task": {
            "name": "识别声音发生的场景",
            "label": "indoor",
            "answer": "是在室内录的。"
        }
    },
    {
        "audio": "audio/GKwRIasH5j8zAYwz9AICeRwG-aacv2-48K_23_input.wav",
        "task": {
            "name": "识别声音发生的场景",
            "label": "subway",
            "answer": "这是在地铁站录的。"
        }
    },
    {
        "audio": "audio/lr5TYeSBLV3FnKcE26IdvapjQAJl_10_input.wav",
        "task": {
            "name": "识别声音发生的场景",
            "label": "park",
            "answer": "这是在公园里录的。"
        }
    },
    {
        "audio": "audio/CKwRIMAE0xyBABAAAADNbOyk_19_input.wav",
        "task": {
            "name": "识别声音发生的场景",
            "label": "subway",
            "answer": "这段声音应该是地铁站录的。"
        }
    },
    {
        "audio": "audio/lkwwPZO0aQFA-wg5mdNwDMDWB8rf_6_input.wav",
        "task": {
            "name": "识别声音发生的场景",
            "label": "indoor",
            "answer": "是在室内的。"
        }
    },
    {
        "audio": "audio/CKwRIJIEwMyoAbUYbQDGhksP_7_input.wav",
        "task": {
            "name": "识别声音发生的场景",
            "label": "outdoor",
            "answer": "这个声音是在户外发生的。"
        }
    },
    {
        "audio": "audio/lryty90aslefdPCI_OOcPDVjyLE0_4_input.wav",
        "task": {
            "name": "识别声音发生的场景",
            "label": "outdoor",
            "answer": "这是在户外录的。"
        }
    },
    {
        "audio": "audio/GKwRIUEKMNl7AZNN4QLbpvq6_3_input.wav",
        "task": {
            "name": "识别声音发生的场景",
            "label": "kitchen",
            "answer": "这是在厨房录的音。"
        }
    },
    {
        "audio": "audio/lgEplq-SA5SxW4VCL_t39GealsYG_10_input.wav",
        "task": {
            "name": "识别声音发生的场景",
            "label": "indoor",
            "answer": "这是在室内的。"
        }
    },
    {
        "audio": "audio/lojZ6Xl4leT4LG8dGe0IXoh5OClO_9_input.wav",
        "task": {
            "name": "识别声音发生的场景",
            "label": "indoor",
            "answer": "这段声音是在室内发生的。"
        }
    },
    {
        "audio": "audio/lvcSAo5fZvr5zOQnBIiZRdebdx19_18_input.wav",
        "task": {
            "name": "识别声音发生的场景",
            "label": "indoor",
            "answer": "听起来是在室内录的。"
        }
    },
    {
        "audio": "audio/2978426683290502662_hd_6_input.wav",
        "task": {
            "name": "识别声音发生的场景",
            "label": "outdoor",
            "answer": "我觉得声音是在户外发生的。"
        }
    },
    {
        "audio": "audio/lgWFNlIkY3Pt_YgYJr-K-IdoorYJ_8_input.wav",
        "task": {
            "name": "识别声音发生的场景",
            "label": "indoor",
            "answer": "是在室内的环境。"
        }
    },
    {
        "audio": "audio/liRCaMbW_1PAGR46cWSB--0826zP_3_input.wav",
        "task": {
            "name": "识别声音发生的场景",
            "label": "park",
            "answer": "这个声音最有可能是在公园里发生的。"
        }
    },
    {
        "audio": "audio/lgjfVKmIsO8XgYoSZxRMQ9Tc16o__14_input.wav",
        "task": {
            "name": "识别声音发生的场景",
            "label": "outdoor",
            "answer": "这段声音是在户外录制的。"
        }
    },
    {
        "audio": "audio/rssFileVip_18_input.wav",
        "task": {
            "name": "识别声音发生的场景",
            "label": "kitchen",
            "answer": "这个声音是在厨房发生的。"
        }
    },
    {
        "audio": "audio/luN-cDxXczX-jRDc-RCudjMlNdSf_26_input.wav",
        "task": {
            "name": "识别声音发生的场景",
            "label": "indoor",
            "answer": "这是在室内的地方录制的。"
        }
    },
    {
        "audio": "audio/lnZaPoWPrK37HwJZ5pnJnYfF837E_4_input.wav",
        "task": {
            "name": "识别声音发生的场景",
            "label": "kitchen",
            "answer": "这是在厨房里。"
        }
    },
    {
        "audio": "audio/lk8qZgxmc2v1MHPkDmHCLIgbaX39_10_input.wav",
        "task": {
            "name": "识别声音发生的场景",
            "label": "restaurant",
            "answer": "这是在餐厅里。"
        }
    },
    {
        "audio": "audio/CKwRIRwEm103AiH-qgC49PNI-aacv2-48K_4_input.wav",
        "task": {
            "name": "识别声音发生的场景",
            "label": "indoor",
            "answer": "是在室内的。"
        }
    },
    {
        "audio": "audio/lu_oRklv7CwfKPWsn76pUx5Ckv4c_5_input.wav",
        "task": {
            "name": "识别声音发生的场景",
            "label": "subway",
            "answer": "这是在地铁站录的音。"
        }
    },
    {
        "audio": "audio/8321375660_316997_14_input.wav",
        "task": {
            "name": "识别声音发生的场景",
            "label": "outdoor",
            "answer": "这是在户外录的。"
        }
    },
    {
        "audio": "audio/GKwRIW4F7LKrArDecAEboMHa-aacv2-48K_23_input.wav",
        "task": {
            "name": "识别声音发生的场景",
            "label": "park",
            "answer": "这是在公园里的声音。"
        }
    },
    {
        "audio": "audio/ljSpccc4pdPfXUqSz5xKJNGw0RX-_3_input.wav",
        "task": {
            "name": "识别声音发生的场景",
            "label": "subway",
            "answer": "这是在地铁站录的音。"
        }
    },
    {
        "audio": "audio/lqysXc84LW0yGvddSerjHuYCzEg6_7_input.wav",
        "task": {
            "name": "识别声音发生的场景",
            "label": "kitchen",
            "answer": "这是在厨房里。"
        }
    },
    {
        "audio": "audio/GKwRIRwHxATDAgUkcAH4obQt-aacv2-48K_8_input.wav",
        "task": {
            "name": "识别声音发生的场景",
            "label": "park",
            "answer": "这是在公园里录的。"
        }
    }
]